pyprlink/__init__.py
pyprlink/main.py
pyprlink/tcp_client.py
pyprlink-0.1.3.dist-info/METADATA
pyprlink-0.1.3.dist-info/WHEEL
pyprlink-0.1.3.dist-info/entry_points.txt
pyprlink-0.1.3.dist-info/top_level.txt
pyprlink-0.1.3.dist-info/RECORD
