Metadata-Version: 2.4
Name: pyprlink
Version: 0.1.3
Summary: TCP/IP client for communicating with PriarieView
Author-email: Jenu Chacko <jenu.chacko@wisc.com>
License: MIT
Project-URL: Homepage, https://github.com/JenuC/PyPrLink
Project-URL: Bug Tracker, https://github.com/JenuC/PyPrLink/issues
Project-URL: Source Code, https://github.com/jenuv/PyPrLink
Keywords: prairie-view,microscopy,bruker-fm
Classifier: Development Status :: 4 - Beta
Classifier: Intended Audience :: Science/Research
Classifier: License :: OSI Approved :: MIT License
Classifier: Programming Language :: Python :: 3
Classifier: Programming Language :: Python :: 3.13
Classifier: Topic :: Scientific/Engineering :: Bio-Informatics
Requires-Python: >=3.10
Requires-Dist: python-dotenv
Provides-Extra: dev
Requires-Dist: pytest; extra == "dev"
